hwcounter.cpython-36m-darwin.so
hwcounter-0.1.1.dist-info/DESCRIPTION.rst
hwcounter-0.1.1.dist-info/METADATA
hwcounter-0.1.1.dist-info/RECORD
hwcounter-0.1.1.dist-info/WHEEL
hwcounter-0.1.1.dist-info/metadata.json
hwcounter-0.1.1.dist-info/top_level.txt
