Metadata-Version: 2.0
Name: hwcounter
Version: 0.1.1
Summary: Highly accurate counter for measuring elapsed time in Python
Home-page: https://github.com/paulsmith/hwcounter
Author: Paul Smith
Author-email: paulsmith@pobox.com
License: UNKNOWN
Keywords: benchmark x86 rdtsc timing
Platform: UNKNOWN
Classifier: Development Status :: 3 - Alpha
Classifier: Intended Audience :: Developers
Classifier: Topic :: System :: Benchmark
Classifier: License :: OSI Approved :: Apache Software License
Classifier: Programming Language :: Python :: 3
Classifier: Programming Language :: Python :: 3.4
Classifier: Programming Language :: Python :: 3.5
Classifier: Programming Language :: Python :: 3.6
